LICENSE
MANIFEST.in
README
setup.py
bflb_iot_tool/__init__.py
bflb_iot_tool/__main__.py
bflb_iot_tool/config.py
bflb_iot_tool/chips/bl602/builtin_imgs/boot2_isp_bl602_v6.5.6/boot2_isp_debug.bin
bflb_iot_tool/chips/bl602/builtin_imgs/boot2_isp_bl602_v6.5.6/boot2_isp_release.bin
bflb_iot_tool/chips/bl602/builtin_imgs/mfg_v2.79/gu/mfg_gu_d8b60c85c_24m.bin
bflb_iot_tool/chips/bl602/builtin_imgs/mfg_v2.79/gu/mfg_gu_d8b60c85c_24m_autoboot.bin
bflb_iot_tool/chips/bl602/builtin_imgs/mfg_v2.79/gu/mfg_gu_d8b60c85c_26m.bin
bflb_iot_tool/chips/bl602/builtin_imgs/mfg_v2.79/gu/mfg_gu_d8b60c85c_26m_autoboot.bin
bflb_iot_tool/chips/bl602/builtin_imgs/mfg_v2.79/gu/mfg_gu_d8b60c85c_32m.bin
bflb_iot_tool/chips/bl602/builtin_imgs/mfg_v2.79/gu/mfg_gu_d8b60c85c_32m_autoboot.bin
bflb_iot_tool/chips/bl602/builtin_imgs/mfg_v2.79/gu/mfg_gu_d8b60c85c_38p4m.bin
bflb_iot_tool/chips/bl602/builtin_imgs/mfg_v2.79/gu/mfg_gu_d8b60c85c_38p4m_autoboot.bin
bflb_iot_tool/chips/bl602/builtin_imgs/mfg_v2.79/gu/mfg_gu_d8b60c85c_40m.bin
bflb_iot_tool/chips/bl602/builtin_imgs/mfg_v2.79/gu/mfg_gu_d8b60c85c_40m_autoboot.bin
bflb_iot_tool/chips/bl602/builtin_imgs/mfg_v2.79/ram/mfg_ram_d8b60c85c_24m.bin
bflb_iot_tool/chips/bl602/builtin_imgs/mfg_v2.79/ram/mfg_ram_d8b60c85c_26m.bin
bflb_iot_tool/chips/bl602/builtin_imgs/mfg_v2.79/ram/mfg_ram_d8b60c85c_32m.bin
bflb_iot_tool/chips/bl602/builtin_imgs/mfg_v2.79/ram/mfg_ram_d8b60c85c_38p4m.bin
bflb_iot_tool/chips/bl602/builtin_imgs/mfg_v2.79/ram/mfg_ram_d8b60c85c_40m.bin
bflb_iot_tool/chips/bl602/conf/ota.toml
bflb_iot_tool/chips/bl602/device_tree/bl_factory_params_IoTKitA_24M.dts
bflb_iot_tool/chips/bl602/device_tree/bl_factory_params_IoTKitA_26M.dts
bflb_iot_tool/chips/bl602/device_tree/bl_factory_params_IoTKitA_32M.dts
bflb_iot_tool/chips/bl602/device_tree/bl_factory_params_IoTKitA_38.4M.dts
bflb_iot_tool/chips/bl602/device_tree/bl_factory_params_IoTKitA_40M.dts
bflb_iot_tool/chips/bl602/device_tree/bl_factory_params_IoTKitA_None.dts
bflb_iot_tool_uart.egg-info/PKG-INFO
bflb_iot_tool_uart.egg-info/SOURCES.txt
bflb_iot_tool_uart.egg-info/dependency_links.txt
bflb_iot_tool_uart.egg-info/entry_points.txt
bflb_iot_tool_uart.egg-info/not-zip-safe
bflb_iot_tool_uart.egg-info/requires.txt
bflb_iot_tool_uart.egg-info/top_level.txt